download_boss/__init__.py
download_boss/api/OpenSearchAPI.py
download_boss/api/__init__.py
download_boss/auth_generator/AbstractAuthGenerator.py
download_boss/auth_generator/AwsAuthGenerator.py
download_boss/auth_generator/BasicAuthGenerator.py
download_boss/auth_generator/RequestsAwsAuthGenerator.py
download_boss/auth_generator/__init__.py
download_boss/client/AbstractClient.py
download_boss/client/Boto3LogsClient.py
download_boss/client/HttpClient.py
download_boss/client/__init__.py
download_boss/client/request/AbstractRequestEnvelope.py
download_boss/client/request/Boto3LogsRequestEnvelope.py
download_boss/client/request/HttpRequestEnvelope.py
download_boss/client/request/__init__.py
download_boss/error/AuthFailed.py
download_boss/error/CachedFileExpired.py
download_boss/error/CachedFileNotFound.py
download_boss/error/ClientRetriable.py
download_boss/error/RetriesExhausted.py
download_boss/error/__init__.py
download_boss/util/Logs.py
download_boss/util/__init__.py
download_boss/wrapper/AbstractWrapper.py
download_boss/wrapper/DelayWrapper.py
download_boss/wrapper/FileCacheWrapper.py
download_boss/wrapper/RetryWrapper.py
download_boss/wrapper/__init__.py
download_boss-0.0.9.dist-info/licenses/LICENSE
download_boss-0.0.9.dist-info/METADATA
download_boss-0.0.9.dist-info/WHEEL
download_boss-0.0.9.dist-info/top_level.txt
download_boss-0.0.9.dist-info/RECORD
