Metadata-Version: 2.4
Name: download_boss
Version: 0.0.9
Summary: Python download library
Author: kristof9851
Project-URL: Homepage, https://github.com/kristof9851/download_boss
Project-URL: Issues, https://github.com/kristof9851/download_boss/issues
Classifier: Topic :: Software Development :: Libraries :: Python Modules
Classifier: Intended Audience :: Developers
Classifier: Programming Language :: Python
Classifier: Programming Language :: Python :: 3.10
Classifier: License :: OSI Approved :: MIT License
Requires-Python: >=3.10
License-File: LICENSE
Dynamic: license-file
